odoo8_addon_medical_patient_ethnicity-8.0.1.1.0.99.dev2-py2.7-nspkg.pth
odoo_addons/medical_patient_ethnicity/__openerp__.py
odoo_addons/medical_patient_ethnicity/__init__.py
odoo_addons/medical_patient_ethnicity/README.rst
odoo_addons/medical_patient_ethnicity/security/ir.model.access.csv
odoo_addons/medical_patient_ethnicity/models/medical_patient.py
odoo_addons/medical_patient_ethnicity/models/medical_patient_ethnicity.py
odoo_addons/medical_patient_ethnicity/models/__init__.py
odoo_addons/medical_patient_ethnicity/i18n/pt_BR.po
odoo_addons/medical_patient_ethnicity/views/medical_patient_ethnicity_view.xml
odoo_addons/medical_patient_ethnicity/views/medical_patient_view.xml
odoo8_addon_medical_patient_ethnicity-8.0.1.1.0.99.dev2.dist-info/top_level.txt
odoo8_addon_medical_patient_ethnicity-8.0.1.1.0.99.dev2.dist-info/WHEEL
odoo8_addon_medical_patient_ethnicity-8.0.1.1.0.99.dev2.dist-info/RECORD
odoo8_addon_medical_patient_ethnicity-8.0.1.1.0.99.dev2.dist-info/metadata.json
odoo8_addon_medical_patient_ethnicity-8.0.1.1.0.99.dev2.dist-info/DESCRIPTION.rst
odoo8_addon_medical_patient_ethnicity-8.0.1.1.0.99.dev2.dist-info/METADATA
odoo8_addon_medical_patient_ethnicity-8.0.1.1.0.99.dev2.dist-info/namespace_packages.txt
